{
  "project_info": {
    "project_number": "684131668449",
    "firebase_url": "https://funation-app-test.firebaseio.com",
    "project_id": "funation-app-test",
    "storage_bucket": "funation-app-test.appspot.com"
  },
  "client": [
    {
      "client_info": {
        "mobilesdk_app_id": "1:684131668449:android:afc4a9c9606dfd8ee342a0",
        "android_client_info": {
          "package_name": "com.example.netflix_clone_practice"
        }
      },
      "oauth_client": [
        {
          "client_id": "684131668449-k9v1h63q5ha5f0s19vh4o3mrukpl0nta.apps.googleusercontent.com",
          "client_type": 3
        }
      ],
      "api_key": [
        {
          "current_key": "AIzaSyAzGPBf_ju8dB5mPgLQxHVVAOMyzZQkadM"
        }
      ],
      "services": {
        "appinvite_service": {
          "other_platform_oauth_client": [
            {
              "client_id": "684131668449-k9v1h63q5ha5f0s19vh4o3mrukpl0nta.apps.googleusercontent.com",
              "client_type": 3
            }
          ]
        }
      }
    },
    {
      "client_info": {
        "mobilesdk_app_id": "1:684131668449:android:80ab3786c5d5d64ee342a0",
        "android_client_info": {
          "package_name": "com.gmuffiness.funation_app_test"
        }
      },
      "oauth_client": [
        {
          "client_id": "684131668449-k9v1h63q5ha5f0s19vh4o3mrukpl0nta.apps.googleusercontent.com",
          "client_type": 3
        }
      ],
      "api_key": [
        {
          "current_key": "AIzaSyAzGPBf_ju8dB5mPgLQxHVVAOMyzZQkadM"
        }
      ],
      "services": {
        "appinvite_service": {
          "other_platform_oauth_client": [
            {
              "client_id": "684131668449-k9v1h63q5ha5f0s19vh4o3mrukpl0nta.apps.googleusercontent.com",
              "client_type": 3
            }
          ]
        }
      }
    }
  ],
  "configuration_version": "1"
}